hcs_grpc_client/__init__.py
hcs_grpc_client/basic_types_pb2.py
hcs_grpc_client/consensus_service_pb2.py
hcs_grpc_client/consensus_service_pb2_grpc.py
hcs_grpc_client/consensus_submit_message_pb2.py
hcs_grpc_client/timestamp_pb2.py
hcs_grpc_client-0.20.0.dist-info/LICENSE
hcs_grpc_client-0.20.0.dist-info/METADATA
hcs_grpc_client-0.20.0.dist-info/WHEEL
hcs_grpc_client-0.20.0.dist-info/top_level.txt
hcs_grpc_client-0.20.0.dist-info/RECORD
