Metadata-Version: 2.1
Name: hcs-grpc-client
Version: 0.20.0
Summary: Hedera HCS gRPC API Python Client
Home-page: https://github.com/wensheng/hcs-grpc-api-py-client
Author: Wensheng Wang
Author-email: wenshengwang@gmail.com
License: UNKNOWN
Project-URL: Bug Tracker, https://github.com/wensheng/hcs-grpc-api-py-client/issues
Platform: UNKNOWN
Classifier: Programming Language :: Python :: 3
Classifier: License :: OSI Approved :: Apache Software License
Classifier: Operating System :: OS Independent
Requires-Python: >=3.6
License-File: LICENSE
Requires-Dist: grpcio (>=1.38.1)
Requires-Dist: protobuf (>=3.17.3)
